csvfile.py
csvfile-3.3.0.dist-info/METADATA
csvfile-3.3.0.dist-info/WHEEL
csvfile-3.3.0.dist-info/top_level.txt
csvfile-3.3.0.dist-info/RECORD
