Metadata-Version: 2.1
Name: csvfile
Version: 3.3.0
Summary: A simple way of working with csv files.
Home-page: https://github.com/imbolc/csvfile
Author: Imbolc
Author-email: imbolc@imbolc.name
License: ISC
Platform: UNKNOWN
Classifier: Development Status :: 4 - Beta
Classifier: Intended Audience :: Developers
Classifier: License :: OSI Approved :: ISC License (ISCL)
Classifier: Programming Language :: Python
Classifier: Programming Language :: Python :: 3
